{
  "generation_date": "2025-12-03T14:20:04.145827",
  "n_taps_specified": 640000,
  "n_taps_actual": 640000,
  "sample_rate_input": 352800,
  "sample_rate_output": 705600,
  "upsample_ratio": 2,
  "passband_end_hz": 20000,
  "stopband_start_hz": 176400,
  "target_stopband_attenuation_db": 160,
  "kaiser_beta": 28.0,
  "phase_type": "hybrid",
  "minimum_phase_method": "homomorphic",
  "hybrid_crossover_hz": 150.0,
  "hybrid_transition_hz": 40.0,
  "hybrid_delay_ms": 6.666666666666667,
  "hybrid_fast_window_samples": 32768,
  "hybrid_fast_window_target_ratio": 0.99,
  "target_dc_gain": 2.0,
  "output_basename": "filter_44k_2x_2m_hybrid_phase",
  "validation_results": {
    "passband_ripple_db": 6.859970859536814,
    "stopband_attenuation_db": 63.38825560205287,
    "max_coefficient_amplitude": 2.0086123915246406,
    "peak_position": 4704,
    "peak_threshold_samples": 6400,
    "energy_ratio_first_to_second_half": 1230282752487.3381,
    "meets_stopband_spec": false,
    "meets_passband_spec": false,
    "passband_ripple_target_db": 0.1,
    "meets_max_coefficient_spec": false,
    "max_coefficient_limit": 1.05,
    "is_minimum_phase": true,
    "is_symmetric": false,
    "phase_type": "hybrid",
    "actual_taps": 640000,
    "fast_window_samples": 32768,
    "fast_window_energy_ratio": 0.9999829391916745,
    "fast_window_target_ratio": 0.99,
    "meets_fast_window_spec": true,
    "hybrid_gain_alignment": {
      "target_band_start_hz": 75.0,
      "target_band_end_hz": 225.0,
      "passband_reference_db": -7.940566414612012e-15,
      "low_gain": 0.9999999927495592,
      "low_gain_db": -6.297652816819773e-08,
      "low_band_db": 7.266126162871195e-11,
      "low_band_start_hz": 0.0,
      "low_band_end_hz": 150.0,
      "high_gain": 1.0,
      "high_gain_db": 0.0,
      "high_band_db": -9.490841736402834e-15,
      "high_band_start_hz": 150.0,
      "high_band_end_hz": 300.0,
      "gain_limit_db": 8.0,
      "low_gain_db_peak": 6.304930956047592e-08,
      "transition_start_hz": 130.0,
      "transition_end_hz": 170.0,
      "crossover_hz": 150.0
    },
    "normalization": {
      "original_dc_gain": 0.548254099668484,
      "target_dc_gain": 2.0,
      "dc_gain_factor": 0.99,
      "normalized_dc_gain": 1.9800000000000006,
      "applied_scale": 3.6114641024978344,
      "l1_norm": 26.080742133290727,
      "l1_norm_ratio": 13.040371066645363,
      "max_coefficient_amplitude": 2.0086123915246406,
      "normalization_applied": true
    }
  }
}